scanpak/__init__.py
scanpak/cli.py
scanpak-0.1.0.dist-info/METADATA
scanpak-0.1.0.dist-info/WHEEL
scanpak-0.1.0.dist-info/entry_points.txt
scanpak-0.1.0.dist-info/top_level.txt
scanpak-0.1.0.dist-info/RECORD
